Pipfile.lock
setup.cfg
setup.py
khopesh/__init__.py
khopesh/app.py
khopesh.egg-info/PKG-INFO
khopesh.egg-info/SOURCES.txt
khopesh.egg-info/dependency_links.txt
khopesh.egg-info/entry_points.txt
khopesh.egg-info/requires.txt
khopesh.egg-info/top_level.txt