Metadata-Version: 1.1
Name: khopesh
Version: 0.0.1
Summary: UNKNOWN
Home-page: https://github.com/Varkal/khopesh
Author: UNKNOWN
Author-email: moreau.romain83@gmail.com
License: MIT
Download-URL: https://github.com/Varkal/khopesh/archive/0.0.1.tar.gz
Keywords: Khopesh
Platform: UNKNOWN
Classifier: Programming Language :: Python :: 3
Classifier: Development Status :: 3 - Alpha
Classifier: Intended Audience :: Developers
